{
  "client": [
    {
      "name": "Interpreter E",
      "langue": "Portugais",
      "date": "2024-08-12",
      "heure": "13:00:00",
      "status": "pending",
      "id": 3
    },
    {
      "name": "Interpreter G",
      "langue": "Chinois",
      "date": "2024-08-14",
      "heure": "15:15:00",
      "status": "pending",
      "id": 5
    },
    {
      "name": "Interpreter H",
      "langue": "Japonais",
      "date": "2024-08-15",
      "heure": "16:00:00",
      "status": "pending",
      "id": 6
    },
    {
      "name": "Client Fs",
      "langue": "Néerlandais",
      "date": "2024-08-13",
      "heure": "14:00:00",
      "status": "pending",
      "id": 7
    },
    {
      "id": 8,
      "name": "Client G",
      "langue": "Chinois",
      "date": "2024-08-14",
      "heure": "15:15:00",
      "status": "pending"
    },
    {
      "id": 9,
      "name": "Client H",
      "langue": "Japonais",
      "date": "2024-08-15",
      "heure": "16:00:00",
      "status": "pending"
    },
    {
      "id": 10,
      "name": "Client I",
      "langue": "Coréen",
      "date": "2024-08-16",
      "heure": "17:30:00",
      "status": "pending"
    },
    {
      "id": 11,
      "name": "Client J",
      "langue": "Arabe",
      "date": "2024-08-17",
      "heure": "18:00:00",
      "status": "pending"
    },
    {
      "name": "khalil",
      "langue": "francais",
      "date": "dsdqfsdqfdsq",
      "heure": "ffdsqf",
      "status": "qfsdsqdf",
      "id": 15
    },
    {
      "name": "Test Clients",
      "langue": "Francais",
      "date": "2024-08-07",
      "heure": "14:30:00",
      "status": "pending",
      "id": 17
    },
    {
      "name": "Test Client",
      "langue": "Francais",
      "date": "2024-08-07",
      "heure": "14:30:00",
      "status": "pending",
      "id": 18
    },
    {
      "name": "Yassir",
      "langue": "Anglais",
      "date": "2024-08-09\t",
      "heure": "10:15:23",
      "status": "in process",
      "id": 19
    },
    {
      "name": "gf",
      "langue": "fgds",
      "date": "sfdg",
      "heure": "dsfg",
      "status": "sdgf",
      "id": 20
    },
    {
      "name": "",
      "langue": "",
      "date": "",
      "heure": "",
      "status": "",
      "id": 21
    },
    {
      "name": "",
      "langue": "",
      "date": "",
      "heure": "",
      "status": "",
      "id": 22
    },
    {
      "name": "",
      "langue": "",
      "date": "",
      "heure": "",
      "status": "",
      "id": 23
    }
  ],
  "interpreter": [
    {
      "name": "Interpreter Cd",
      "langue": "Allemand",
      "date": "2024-08-10",
      "heure": "11:00:00",
      "status": "pending",
      "id": 1
    },
    {
      "id": 2,
      "name": "Interpreter D",
      "langue": "Italien",
      "date": "2024-08-11",
      "heure": "12:30:00",
      "status": "pending"
    },
    {
      "id": 3,
      "name": "Interpreter E",
      "langue": "Portugais",
      "date": "2024-08-12",
      "heure": "13:00:00",
      "status": "pending"
    },
    {
      "id": 4,
      "name": "Interpreter F",
      "langue": "Néerlandais",
      "date": "2024-08-13",
      "heure": "14:00:00",
      "status": "pending"
    },
    {
      "id": 5,
      "name": "Interpreter G",
      "langue": "Chinois",
      "date": "2024-08-14",
      "heure": "15:15:00",
      "status": "pending"
    },
    {
      "id": 6,
      "name": "Interpreter H",
      "langue": "Japonais",
      "date": "2024-08-15",
      "heure": "16:00:00",
      "status": "pending"
    },
    {
      "id": 7,
      "name": "Interpreter I",
      "langue": "Coréen",
      "date": "2024-08-16",
      "heure": "17:30:00",
      "status": "pending"
    },
    {
      "id": 8,
      "name": "Interpreter J",
      "langue": "Arabe",
      "date": "2024-08-17",
      "heure": "18:00:00",
      "status": "pending"
    }
  ],
  "invoices": [
    {
      "id": 1,
      "client": "John Doe",
      "amount": 150.75,
      "date": "2024-08-01",
      "status": "Paid"
    },
    {
      "id": 2,
      "client": "Jane Smith",
      "amount": 200,
      "date": "2024-08-03",
      "status": "Unpaid"
    },
    {
      "id": 3,
      "client": "Acme Corp",
      "amount": 450.5,
      "date": "2024-08-07",
      "status": "Pending"
    },
    {
      "id": 4,
      "client": "Global Inc",
      "amount": 1250,
      "date": "2024-08-10",
      "status": "Paid"
    },
    {
      "id": 5,
      "client": "Sarah Johnson",
      "amount": 350.25,
      "date": "2024-08-12",
      "status": "Unpaid"
    }
  ]
}